antimony/__init__.py
antimony/antimony.py
antimony/libantimony.so
antimony-3.1.0.dist-info/METADATA
antimony-3.1.0.dist-info/WHEEL
antimony-3.1.0.dist-info/top_level.txt
antimony-3.1.0.dist-info/RECORD
