Metadata-Version: 2.4
Name: antimony
Version: 3.1.0
Summary: Python bindings for libAntimony
Home-page: http://antimony.sf.net/
Author: Lucian Smith
Author-email: lpsmith@uw.edu
License: MIT
Dynamic: author
Dynamic: author-email
Dynamic: description
Dynamic: description-content-type
Dynamic: home-page
Dynamic: license
Dynamic: summary
